[[{"start":"10:30","finish":"12:05","name":"История России","rooms":["П-6"],"teachers":["Меркулова Анастасия Михайловна"]},{"start":"12:50","finish":"14:25","name":"Математический анализ","rooms":["П-6"],"teachers":["профессор Фомичёв Василий Владимирович"]},{"start":"14:35","finish":"16:10","name":null,"rooms":["785"],"teachers":["Русский язык Хлопьянов А.В."]},{"start":"16:50","finish":"18:20","name":"Физическая культура","rooms":[null],"teachers":[null]}],[{"start":"8:45","finish":"10:20","name":"Английский язык","rooms":["71","786"],"teachers":["Перцева З.Е.","Шабловский А.А."]},{"start":"10:30","finish":"12:05","name":"Архитектура ЭВМ и язык Ассемблера","rooms":["П-13"],"teachers":["доцент Бордаченкова Елена Анатольевна"]},{"start":"12:50","finish":"14:25","name":"Алгебра и геометрия П-13 согл","rooms":[null],"teachers":["доцент Панфёров Валерий Семёнович"]},{"start":"14:35","finish":"16:10","name":"Практикум на ЭВМ","rooms":["659","515"],"teachers":["Капитонова А.П. Пашков В.Н."]}],[{"start":"8:45","finish":"10:20","name":"Русский язык и культура речи","rooms":["П-6"],"teachers":["доцент Баданина Ирина Васильевна"]},{"start":"10:30","finish":"12:05","name":"Дискретная математика","rooms":["П-6"],"teachers":["профессор Марченков Сергей Серафимович"]},{"start":"12:50","finish":"14:25","name":"Математический анализ","rooms":["П-6"],"teachers":["профессор Фомичёв Василий Владимирович"]},{"start":"15:10","finish":"18:50","name":"Межфакультетские курсы","rooms":[null],"teachers":[null]},{"start":"15:10","finish":"18:50","name":"Межфакультетские курсы","rooms":[null],"teachers":[null]}],[{"start":"8:45","finish":"10:20","name":"Алгебра и геометрия","rooms":["615"],"teachers":["Морозова В.А."]},{"start":"10:30","finish":"12:05","name":"Английский язык","rooms":["71","786"],"teachers":["Перцева З.Е.","Шабловский А.А."]},{"start":"12:50","finish":"14:25","name":"Алгебра и геометрия","rooms":["П-14"],"teachers":["доцент Панфёров Валерий Семёнович"]},{"start":"14:35","finish":"16:10","name":"Математический анализ","rooms":["607"],"teachers":["Буничева А.Я."]}],[{"start":"9:00","finish":"10:30","name":"Физическая культура","rooms":[null],"teachers":[null]},{"start":"10:40","finish":"12:15","name":"Архитектура ЭВМ и язык Ассемблера","rooms":["П-13"],"teachers":["доцент Бордаченкова Елена Анатольевна"]},{"start":"12:50","finish":"14:25","name":"Дискретная математика","rooms":["П-5"],"teachers":["профессор Марченков Сергей Серафимович"]},{"start":"14:35","finish":"16:10","name":"Практикум на ЭВМ","rooms":["659","515"],"teachers":["Капитонова А.П. Пашков В.Н."]}],[{"start":"8:45","finish":"10:20","name":"Математический анализ","rooms":["606"],"teachers":["Буничева А.Я."]},{"start":"10:30","finish":"12:05","name":"Алгебра и геометрия","rooms":["624"],"teachers":["Морозова В.А."]},{"start":"12:50","finish":"14:25","name":"Дискретная математика","rooms":[null],"teachers":["Данилов Б.Р."]},{"start":"14:35","finish":"16:10","name":"История России Меркулова А.М..","rooms":["524"],"teachers":[null]}]]